kacl/__init__.py
kacl/__main__.py
kacl/changes.py
kacl/config.py
kacl/document.py
kacl/element.py
kacl/exception.py
kacl/jira_client.py
kacl/kacl_cli.py
kacl/link_provider.py
kacl/parser.py
kacl/serializer.py
kacl/utils.py
kacl/validation.py
kacl/version.py
kacl/config/kacl-default.yml
python_kacl-0.6.7.dist-info/licenses/LICENSE
python_kacl-0.6.7.dist-info/METADATA
python_kacl-0.6.7.dist-info/WHEEL
python_kacl-0.6.7.dist-info/entry_points.txt
python_kacl-0.6.7.dist-info/top_level.txt
python_kacl-0.6.7.dist-info/RECORD
