Metadata-Version: 2.4
Name: python-kacl
Version: 0.6.7
Summary: Python module and CLI tool for validating and modifying Changelogs in "keep-a-changelog" format"
Home-page: https://gitlab.com/schmieder.matthias/python-kacl.git
Author: Matthias Schmieder
Author-email: schmieder.matthias@gmail.com
License: MIT
Classifier: License :: OSI Approved :: MIT License
Classifier: Programming Language :: Python :: 3
Classifier: Programming Language :: Python :: 3.9
Classifier: Intended Audience :: Developers
Classifier: Topic :: Software Development :: Version Control
Requires-Python: >=3.9
License-File: LICENSE
Requires-Dist: click
Requires-Dist: semver
Requires-Dist: gitpython
Requires-Dist: pyyaml
Requires-Dist: jira
Dynamic: author
Dynamic: author-email
Dynamic: classifier
Dynamic: description
Dynamic: description-content-type
Dynamic: home-page
Dynamic: license
Dynamic: license-file
Dynamic: requires-dist
Dynamic: requires-python
Dynamic: summary
